odoo/addons/auth_api_key/README.rst
odoo/addons/auth_api_key/__init__.py
odoo/addons/auth_api_key/__manifest__.py
odoo/addons/auth_api_key/i18n/auth_api_key.pot
odoo/addons/auth_api_key/i18n/it.po
odoo/addons/auth_api_key/i18n/zh_CN.po
odoo/addons/auth_api_key/models/__init__.py
odoo/addons/auth_api_key/models/auth_api_key.py
odoo/addons/auth_api_key/models/ir_http.py
odoo/addons/auth_api_key/models/res_company.py
odoo/addons/auth_api_key/models/res_config_settings.py
odoo/addons/auth_api_key/readme/CONFIGURE.md
odoo/addons/auth_api_key/readme/CONTRIBUTORS.md
odoo/addons/auth_api_key/readme/CREDITS.md
odoo/addons/auth_api_key/readme/DESCRIPTION.md
odoo/addons/auth_api_key/readme/USAGE.md
odoo/addons/auth_api_key/security/ir.model.access.csv
odoo/addons/auth_api_key/static/description/icon.png
odoo/addons/auth_api_key/static/description/index.html
odoo/addons/auth_api_key/tests/__init__.py
odoo/addons/auth_api_key/tests/test_auth_api_key.py
odoo/addons/auth_api_key/views/auth_api_key.xml
odoo/addons/auth_api_key/views/res_config_settings.xml
odoo_addon_auth_api_key-18.0.1.0.1.dist-info/METADATA
odoo_addon_auth_api_key-18.0.1.0.1.dist-info/WHEEL
odoo_addon_auth_api_key-18.0.1.0.1.dist-info/top_level.txt
odoo_addon_auth_api_key-18.0.1.0.1.dist-info/RECORD
